[{"model": "flatpages.flatpage_sites", "pk": 1, "fields": {"flatpage": 1, "site": 1}}, {"model": "flatpages.flatpage_sites", "pk": 2, "fields": {"flatpage": 2, "site": 1}}, {"model": "flatpages.flatpage_sites", "pk": 3, "fields": {"flatpage": 3, "site": 1}}, {"model": "flatpages.flatpage_sites", "pk": 4, "fields": {"flatpage": 4, "site": 1}}, {"model": "flatpages.flatpage_sites", "pk": 5, "fields": {"flatpage": 5, "site": 1}}, {"model": "flatpages.flatpage_sites", "pk": 6, "fields": {"flatpage": 6, "site": 1}}, {"model": "flatpages.flatpage_sites", "pk": 7, "fields": {"flatpage": 7, "site": 1}}, {"model": "flatpages.flatpage_sites", "pk": 8, "fields": {"flatpage": 8, "site": 1}}, {"model": "flatpages.flatpage_sites", "pk": 9, "fields": {"flatpage": 9, "site": 1}}, {"model": "flatpages.flatpage_sites", "pk": 10, "fields": {"flatpage": 10, "site": 1}}, {"model": "flatpages.flatpage_sites", "pk": 11, "fields": {"flatpage": 11, "site": 1}}, {"model": "flatpages.flatpage_sites", "pk": 12, "fields": {"flatpage": 12, "site": 1}}, {"model": "flatpages.flatpage_sites", "pk": 13, "fields": {"flatpage": 13, "site": 1}}, {"model": "flatpages.flatpage_sites", "pk": 14, "fields": {"flatpage": 14, "site": 1}}, {"model": "flatpages.flatpage_sites", "pk": 15, "fields": {"flatpage": 15, "site": 1}}, {"model": "flatpages.flatpage_sites", "pk": 16, "fields": {"flatpage": 16, "site": 1}}, {"model": "flatpages.flatpage_sites", "pk": 17, "fields": {"flatpage": 17, "site": 1}}, {"model": "flatpages.flatpage_sites", "pk": 18, "fields": {"flatpage": 18, "site": 1}}, {"model": "flatpages.flatpage_sites", "pk": 19, "fields": {"flatpage": 19, "site": 1}}, {"model": "flatpages.flatpage_sites", "pk": 20, "fields": {"flatpage": 20, "site": 1}}, {"model": "flatpages.flatpage_sites", "pk": 21, "fields": {"flatpage": 21, "site": 1}}, {"model": "flatpages.flatpage_sites", "pk": 22, "fields": {"flatpage": 22, "site": 1}}, {"model": "flatpages.flatpage_sites", "pk": 23, "fields": {"flatpage": 23, "site": 1}}, {"model": "flatpages.flatpage_sites", "pk": 24, "fields": {"flatpage": 24, "site": 1}}, {"model": "flatpages.flatpage_sites", "pk": 25, "fields": {"flatpage": 25, "site": 1}}, {"model": "flatpages.flatpage_sites", "pk": 26, "fields": {"flatpage": 26, "site": 1}}, {"model": "flatpages.flatpage_sites", "pk": 27, "fields": {"flatpage": 27, "site": 1}}, {"model": "flatpages.flatpage_sites", "pk": 28, "fields": {"flatpage": 28, "site": 1}}, {"model": "flatpages.flatpage_sites", "pk": 29, "fields": {"flatpage": 29, "site": 1}}, {"model": "flatpages.flatpage_sites", "pk": 30, "fields": {"flatpage": 30, "site": 1}}, {"model": "flatpages.flatpage_sites", "pk": 31, "fields": {"flatpage": 31, "site": 1}}, {"model": "flatpages.flatpage_sites", "pk": 32, "fields": {"flatpage": 32, "site": 1}}, {"model": "flatpages.flatpage_sites", "pk": 33, "fields": {"flatpage": 33, "site": 1}}, {"model": "flatpages.flatpage_sites", "pk": 34, "fields": {"flatpage": 34, "site": 1}}, {"model": "flatpages.flatpage_sites", "pk": 35, "fields": {"flatpage": 35, "site": 1}}, {"model": "flatpages.flatpage_sites", "pk": 36, "fields": {"flatpage": 36, "site": 1}}, {"model": "flatpages.flatpage_sites", "pk": 37, "fields": {"flatpage": 37, "site": 1}}]