[{"model": "vol.forcatarefa", "pk": 1, "fields": {"tarefa": "descobrir o e-mail de entidades", "codigo": "cata-email", "data_cadastro": "2020-06-03T15:20:25.572Z", "meta": 1061, "modelo": "Entidade", "filtro": "{'aprovado': True, 'vinculoentidade__isnull': True, 'email_set__isnull': True}", "url": "/iadm/vol/entidadesememail/", "visivel": true, "orientacoes": 1}}, {"model": "vol.forcatarefa", "pk": 2, "fields": {"tarefa": "revisar entidades de Franca/SP", "codigo": "francamente", "data_cadastro": "2020-09-26T23:08:53.174Z", "meta": 17, "modelo": "Entidade", "filtro": "{'aprovado': True, 'cidade__iexact': 'franca', 'estado': 'SP', 'anotacaoentidade_set__isnull': True}", "url": "/iadm/vol/entidadedefranca/", "visivel": true, "orientacoes": 3}}]